odoo10_addon_l10n_ch_lsv_dd-10.0.1.0.0-py2.7-nspkg.pth
odoo/addons/l10n_ch_lsv_dd/README.rst
odoo/addons/l10n_ch_lsv_dd/__init__.py
odoo/addons/l10n_ch_lsv_dd/__manifest__.py
odoo/addons/l10n_ch_lsv_dd/data/README.md
odoo/addons/l10n_ch_lsv_dd/data/export_filename_sequence.xml
odoo/addons/l10n_ch_lsv_dd/data/pain.008.001.02.ch.03.xsd
odoo/addons/l10n_ch_lsv_dd/data/payment_type.xml
odoo/addons/l10n_ch_lsv_dd/demo/lsv_dd_demo.xml
odoo/addons/l10n_ch_lsv_dd/demo/lsv_dd_demo.yml
odoo/addons/l10n_ch_lsv_dd/migrations/9.0.1.0.0/pre-migration.py
odoo/addons/l10n_ch_lsv_dd/models/__init__.py
odoo/addons/l10n_ch_lsv_dd/models/account_payment_method.py
odoo/addons/l10n_ch_lsv_dd/models/account_payment_order.py
odoo/addons/l10n_ch_lsv_dd/models/bank.py
odoo/addons/l10n_ch_lsv_dd/models/banking_export_ch_dd.py
odoo/addons/l10n_ch_lsv_dd/models/move_line.py
odoo/addons/l10n_ch_lsv_dd/security/ir.model.access.csv
odoo/addons/l10n_ch_lsv_dd/tests/__init__.py
odoo/addons/l10n_ch_lsv_dd/tests/test_bank.py
odoo/addons/l10n_ch_lsv_dd/tests/test_dd_export_wizard.py
odoo/addons/l10n_ch_lsv_dd/tests/test_lsv_dd.py
odoo/addons/l10n_ch_lsv_dd/tests/test_lsv_export_wizard.py
odoo/addons/l10n_ch_lsv_dd/views/account_payment_line_view.xml
odoo/addons/l10n_ch_lsv_dd/views/account_payment_method_view.xml
odoo/addons/l10n_ch_lsv_dd/views/account_payment_mode_view.xml
odoo/addons/l10n_ch_lsv_dd/views/account_payment_order_view.xml
odoo/addons/l10n_ch_lsv_dd/views/bank_payment_line_view.xml
odoo/addons/l10n_ch_lsv_dd/views/bank_view.xml
odoo/addons/l10n_ch_lsv_dd/views/banking_export_ch_dd_view.xml
odoo/addons/l10n_ch_lsv_dd/views/dd_export_wizard_view.xml
odoo/addons/l10n_ch_lsv_dd/views/lsv_export_wizard_view.xml
odoo/addons/l10n_ch_lsv_dd/wizards/__init__.py
odoo/addons/l10n_ch_lsv_dd/wizards/dd_export_wizard.py
odoo/addons/l10n_ch_lsv_dd/wizards/export_utils.py
odoo/addons/l10n_ch_lsv_dd/wizards/lsv_export_wizard.py
odoo10_addon_l10n_ch_lsv_dd-10.0.1.0.0.dist-info/DESCRIPTION.rst
odoo10_addon_l10n_ch_lsv_dd-10.0.1.0.0.dist-info/METADATA
odoo10_addon_l10n_ch_lsv_dd-10.0.1.0.0.dist-info/RECORD
odoo10_addon_l10n_ch_lsv_dd-10.0.1.0.0.dist-info/WHEEL
odoo10_addon_l10n_ch_lsv_dd-10.0.1.0.0.dist-info/metadata.json
odoo10_addon_l10n_ch_lsv_dd-10.0.1.0.0.dist-info/namespace_packages.txt
odoo10_addon_l10n_ch_lsv_dd-10.0.1.0.0.dist-info/top_level.txt
