Metadata-Version: 2.0
Name: odoo10-addon-l10n-ch-lsv-dd
Version: 10.0.1.0.0
Summary: Create LSV and Direct Debit (postfinance) files
Home-page: http://www.compassion.ch,http://www.braintec-group.com
Author: brain-tec AG,Compassion,Odoo Community Association (OCA)
Author-email: support@odoo-community.org
License: AGPL-3
Platform: UNKNOWN
Classifier: Programming Language :: Python
Classifier: Framework :: Odoo
Classifier: License :: OSI Approved :: GNU Affero General Public License v3
Requires-Python: ~=2.7
Requires-Dist: odoo (<10.1dev,>=10.0)
Requires-Dist: odoo10-addon-account-banking-sepa-direct-debit
Requires-Dist: odoo10-addon-l10n-ch-payment-slip
